shamsinox/__init__.py
shamsinox/persian_calendar.py
shamsinox-0.1.1.dist-info/licenses/LICENSE
shamsinox-0.1.1.dist-info/METADATA
shamsinox-0.1.1.dist-info/WHEEL
shamsinox-0.1.1.dist-info/top_level.txt
shamsinox-0.1.1.dist-info/RECORD
