Metadata-Version: 2.4
Name: shamsinox
Version: 0.1.1
Summary: A Python library for working with the Persian (Jalali) calendar
Author-email: Arsham Hasanpour <arshammhasanpourrr@gmail.com>
License: MIT
Project-URL: Homepage, https://github.com/ArshamH011/shamsinox
Project-URL: Repository, https://github.com/ArshamH011/shamsinox
Project-URL: Issues, https://github.com/ArshamH011/shamsinox/issues
Classifier: Programming Language :: Python :: 3
Classifier: License :: OSI Approved :: MIT License
Classifier: Operating System :: OS Independent
Requires-Python: >=3.6
License-File: LICENSE
Dynamic: license-file
